SDUOJ/__init__.py
SDUOJ/__main__.py
SDUOJ/ojd.py
SDUOJ/uploadAns.py
SDUOJ/oj/SDUOJ_Manager.py
SDUOJ/oj/__init__.py
SDUOJ/oj/entity.py
SDUOJ/utils/Authenticator.py
SDUOJ/utils/FileHandler.py
SDUOJ/utils/UserInputHandler.py
SDUOJ/utils/__init__.py
SDUOJ/utils/config.py
sduoj-0.0.2.dist-info/METADATA
sduoj-0.0.2.dist-info/WHEEL
sduoj-0.0.2.dist-info/licenses/LICENSE
sduoj-0.0.2.dist-info/RECORD
