Metadata-Version: 2.3
Name: SDUOJ
Version: 0.0.2
Summary: Using SDUOJ on shell
Project-URL: Homepage, https://github.com/Jenway/SDUOJ_on_shell
Project-URL: Issues, https://github.com/Jenway/SDUOJ_on_shell/issues
Author-email: Jenway <JenwayHere@Gmail.com>
License-File: LICENSE
Classifier: License :: OSI Approved :: MIT License
Classifier: Operating System :: OS Independent
Classifier: Programming Language :: Python :: 3
Requires-Python: >=3.8
Requires-Dist: httpx
Requires-Dist: pyinputplus
